setup.py
pyliquib/__init__.py
pyliquib/basechangeset.py
pyliquib/constants.py
pyliquib/inlinejs.py
pyliquib/pycallback.py
pyliquib.egg-info/PKG-INFO
pyliquib.egg-info/SOURCES.txt
pyliquib.egg-info/dependency_links.txt
pyliquib.egg-info/requires.txt
pyliquib.egg-info/top_level.txt