Metadata-Version: 1.0
Name: pyliquib
Version: 0.1.2
Summary: A MongoDB migration tool with pymongo inspired by Liquibase
Home-page: https://github.com/gtsarik/pyliquib
Author: Henadzi Tsaryk
Author-email: vare6gin@gmail.com
License: BSD
Platform: Any
